mockextras-1.0.2.dist-info/metadata.json
mockextras-1.0.2.dist-info/top_level.txt
mockextras-1.0.2.dist-info/RECORD
mockextras-1.0.2.dist-info/DESCRIPTION.rst
mockextras-1.0.2.dist-info/METADATA
mockextras-1.0.2.dist-info/WHEEL
mockextras/_stub.py
mockextras/__init__.py
mockextras/_matchers.py
mockextras/_fluent.py
